<annotation>
	<folder>train</folder>
	<filename>1673699823775.jpg</filename>
	<path>C:\Users\hirunisi\Desktop\dataset\train\1673699823775.jpg</path>
	<source>
		<database>Unknown</database>
	</source>
	<size>
		<width>768</width>
		<height>1024</height>
		<depth>3</depth>
	</size>
	<segmented>0</segmented>
	<object>
		<name>corner_post</name>
		<pose>Unspecified</pose>
		<truncated>1</truncated>
		<difficult>0</difficult>
		<bndbox>
			<xmin>98</xmin>
			<ymin>1</ymin>
			<xmax>758</xmax>
			<ymax>842</ymax>
		</bndbox>
	</object>
</annotation>
