<annotation>
	<folder>train</folder>
	<filename>img_1 (463).jpg</filename>
	<path>C:\IIT\FYP\DataSet\dataset_severity_17.04.2023\train\img_1 (463).jpg</path>
	<source>
		<database>Unknown</database>
	</source>
	<size>
		<width>902</width>
		<height>693</height>
		<depth>3</depth>
	</size>
	<segmented>0</segmented>
	<object>
		<name>moderate</name>
		<pose>Unspecified</pose>
		<truncated>0</truncated>
		<difficult>0</difficult>
		<bndbox>
			<xmin>36</xmin>
			<ymin>390</ymin>
			<xmax>117</xmax>
			<ymax>480</ymax>
		</bndbox>
	</object>
	<object>
		<name>moderate</name>
		<pose>Unspecified</pose>
		<truncated>0</truncated>
		<difficult>0</difficult>
		<bndbox>
			<xmin>668</xmin>
			<ymin>535</ymin>
			<xmax>849</xmax>
			<ymax>629</ymax>
		</bndbox>
	</object>
</annotation>
