<annotation>
	<folder>all_images_2</folder>
	<filename>img_1 (49).jpg</filename>
	<path>C:\DATASET\all_images_2\img_1 (49).jpg</path>
	<source>
		<database>Unknown</database>
	</source>
	<size>
		<width>1560</width>
		<height>2080</height>
		<depth>3</depth>
	</size>
	<segmented>0</segmented>
	<object>
		<name>cut</name>
		<pose>Unspecified</pose>
		<truncated>0</truncated>
		<difficult>0</difficult>
		<bndbox>
			<xmin>184</xmin>
			<ymin>765</ymin>
			<xmax>643</xmax>
			<ymax>1532</ymax>
		</bndbox>
	</object>
</annotation>
